MANIFEST.in
README.txt
setup.py
docs/HISTORY.txt
src/silva/__init__.py
src/silva.core.contentlayout.egg-info/PKG-INFO
src/silva.core.contentlayout.egg-info/SOURCES.txt
src/silva.core.contentlayout.egg-info/dependency_links.txt
src/silva.core.contentlayout.egg-info/entry_points.txt
src/silva.core.contentlayout.egg-info/namespace_packages.txt
src/silva.core.contentlayout.egg-info/not-zip-safe
src/silva.core.contentlayout.egg-info/requires.txt
src/silva.core.contentlayout.egg-info/top_level.txt
src/silva/core/__init__.py
src/silva/core/contentlayout/__init__.py
src/silva/core/contentlayout/configure.zcml
src/silva/core/contentlayout/ftesting.zcml
src/silva/core/contentlayout/interfaces.py
src/silva/core/contentlayout/martiansupport.py
src/silva/core/contentlayout/model.png
src/silva/core/contentlayout/model.py
src/silva/core/contentlayout/service.png
src/silva/core/contentlayout/service.py
src/silva/core/contentlayout/smi.py
src/silva/core/contentlayout/testing.py
src/silva/core/contentlayout/utils.py
src/silva/core/contentlayout/blocks/__init__.py
src/silva/core/contentlayout/blocks/contents.png
src/silva/core/contentlayout/blocks/contents.py
src/silva/core/contentlayout/blocks/edit_slot.cpt
src/silva/core/contentlayout/blocks/manager.py
src/silva/core/contentlayout/blocks/registry.py
src/silva/core/contentlayout/blocks/slot.png
src/silva/core/contentlayout/blocks/slot.py
src/silva/core/contentlayout/blocks/source.png
src/silva/core/contentlayout/blocks/source.py
src/silva/core/contentlayout/blocks/text.png
src/silva/core/contentlayout/blocks/text.py
src/silva/core/contentlayout/defaults/__init__.py
src/silva/core/contentlayout/defaults/blocks.py
src/silva/core/contentlayout/designs/__init__.py
src/silva/core/contentlayout/designs/design.py
src/silva/core/contentlayout/designs/expressions.py
src/silva/core/contentlayout/designs/registry.py
src/silva/core/contentlayout/silvaxml/__init__.py
src/silva/core/contentlayout/silvaxml/xmlexport.py
src/silva/core/contentlayout/silvaxml/xmlimport.py
src/silva/core/contentlayout/slots/__init__.py
src/silva/core/contentlayout/slots/edit_slot.cpt
src/silva/core/contentlayout/slots/restrictions.py
src/silva/core/contentlayout/slots/slot.py
src/silva/core/contentlayout/slots/view_slot.cpt
src/silva/core/contentlayout/smi_templates/components.cpt
src/silva/core/contentlayout/smi_templates/editorsmiconfiguration.cpt
