Metadata-Version: 1.1
Name: silva.core.contentlayout
Version: 3.0.5
Summary: Silva Content Layout engine for Silva CMS
Home-page: https://github.com/silvacms/silva.core.contentlayout
Author: Andrew Altepeter
Author-email: aaltepet@bethel.edu
License: GPL
Platform: UNKNOWN
Classifier: Framework :: Zope2
Classifier: Programming Language :: Python
Classifier: Topic :: Software Development :: Libraries :: Python Modules
